create_fusion_app/__init__.py
create_fusion_app/main.py
create_fusion_app-0.1.18.dist-info/METADATA
create_fusion_app-0.1.18.dist-info/WHEEL
create_fusion_app-0.1.18.dist-info/entry_points.txt
create_fusion_app-0.1.18.dist-info/top_level.txt
create_fusion_app-0.1.18.dist-info/RECORD
